ibkrtools/IBKR_Hist.py
ibkrtools/IBKR_Realitime_Data.py
ibkrtools/__init__.py
ibkrtools/truths.py
ibkrtools/utils.py
ibkrtools-0.1.0.dist-info/licenses/LICENSE
ibkrtools-0.1.0.dist-info/METADATA
ibkrtools-0.1.0.dist-info/WHEEL
ibkrtools-0.1.0.dist-info/top_level.txt
ibkrtools-0.1.0.dist-info/RECORD
