Metadata-Version: 2.4
Name: ibkrtools
Version: 0.1.0
Summary: A modern Python wrapper for Interactive Brokers TWS API
Home-page: https://github.com/StavrosKlaoudatos/IBKRTools
Author: Stavros Klaoudatos
Author-email: stavrosklaoudatos@gmail.com
Keywords: interactive brokers,trading,finance,algorithmic trading,market data
Classifier: Development Status :: 4 - Beta
Classifier: Intended Audience :: Financial and Insurance Industry
Classifier: License :: OSI Approved :: MIT License
Classifier: Operating System :: OS Independent
Classifier: Programming Language :: Python :: 3
Classifier: Programming Language :: Python :: 3.8
Classifier: Programming Language :: Python :: 3.9
Classifier: Programming Language :: Python :: 3.10
Classifier: Programming Language :: Python :: 3.11
Classifier: Programming Language :: Python :: 3.12
Classifier: Topic :: Office/Business :: Financial
Classifier: Topic :: Office/Business :: Financial :: Investment
Classifier: Topic :: Software Development :: Libraries :: Python Modules
Requires-Python: >=3.8
License-File: LICENSE
Requires-Dist: ibapi>=9.81.1
Requires-Dist: pandas>=1.3.0
Requires-Dist: pytz>=2021.1
Requires-Dist: python-dateutil>=2.8.2
Requires-Dist: holidays>=0.13
Dynamic: author
Dynamic: author-email
Dynamic: classifier
Dynamic: description
Dynamic: description-content-type
Dynamic: home-page
Dynamic: keywords
Dynamic: license-file
Dynamic: requires-dist
Dynamic: requires-python
Dynamic: summary
